Metadata-Version: 2.1
Name: pyrim
Version: 0.1
Summary: A Simple and Efficient Image Manipulation Module
Home-page: UNKNOWN
Author: Rounik Mondal
Author-email: rounikmondal74@gmail.com
License: UNKNOWN
Project-URL: Source, https://github.com/Rounik-Nikz/PyRim
Keywords: python,image manupulation,pyrim,rounik,pixels,pillow
Platform: UNKNOWN
Classifier: Development Status :: 5 - Production/Stable
Classifier: Intended Audience :: Education
Classifier: License :: OSI Approved :: MIT License
Classifier: Programming Language :: Python :: 3
Classifier: Programming Language :: Python :: 3.6
Classifier: Programming Language :: Python :: 3.7
Classifier: Programming Language :: Python :: 3.8
Classifier: Programming Language :: Python :: 3.9
Classifier: Programming Language :: Python :: 3 :: Only
